some_file_tools/__init__.py
some_file_tools-1.1.dist-info/LICENSE
some_file_tools-1.1.dist-info/METADATA
some_file_tools-1.1.dist-info/WHEEL
some_file_tools-1.1.dist-info/top_level.txt
some_file_tools-1.1.dist-info/RECORD
