Metadata-Version: 2.1
Name: some-file-tools
Version: 1.1
Summary: A small python package with various helpful methods for working with files.
Home-page: https://github.com/pypa/sampleproject
Author: Daniel Gluch
Author-email: danielgluch33@gmail.com
License: UNKNOWN
Platform: UNKNOWN
Classifier: Programming Language :: Python :: 3
Classifier: License :: OSI Approved :: MIT License
Classifier: Operating System :: OS Independent
Requires-Python: >=3.6
